CHANGES.txt
LICENSE.txt
MANIFEST.in
README.rst
setup.cfg
setup.py
tox.ini
ghtml/__init__.py
ghtml/c_ghtml.py
ghtml.egg-info/PKG-INFO
ghtml.egg-info/SOURCES.txt
ghtml.egg-info/dependency_links.txt
ghtml.egg-info/entry_points.txt
ghtml.egg-info/not-zip-safe
ghtml.egg-info/requires.txt
ghtml.egg-info/top_level.txt
ghtml/tests/__init__.py
ghtml/tests/test_ghtml.py