Metadata-Version: 1.1
Name: ghtml
Version: 0.1.3
Summary: A gobj that generates html.
Home-page: https://bitbucket.org/artgins/ghtml
Author: ginsmar
Author-email: ginsmar at artgins.com
License: MIT License
Keywords: gobj ginsfsm finite state machine fsm html5 css js
Platform: UNKNOWN
Classifier: Intended Audience :: Developers
Classifier: Development Status :: 4 - Beta
Classifier: Programming Language :: Python
Classifier: Programming Language :: Python :: 2
Classifier: Programming Language :: Python :: 2.7
Classifier: License :: OSI Approved :: MIT License
